{"frames":{"fall_2":{"frame":{"x":254,"y":2,"w":64,"h":117},"rotated":false,"trimmed":false,"spriteSourceSize":{"x":0,"y":0,"w":64,"h":117},"sourceSize":{"w":64,"h":117}},"run_1":{"frame":{"x":321,"y":2,"w":64,"h":120},"rotated":false,"trimmed":false,"spriteSourceSize":{"x":0,"y":0,"w":64,"h":120},"sourceSize":{"w":64,"h":120}},"run_2":{"frame":{"x":387,"y":2,"w":63,"h":119},"rotated":false,"trimmed":false,"spriteSourceSize":{"x":0,"y":0,"w":63,"h":119},"sourceSize":{"w":63,"h":119}},"jump_1":{"frame":{"x":2,"y":3,"w":63,"h":116},"rotated":false,"trimmed":false,"spriteSourceSize":{"x":0,"y":0,"w":63,"h":116},"sourceSize":{"w":63,"h":116}},"jump_2":{"frame":{"x":67,"y":3,"w":59,"h":113},"rotated":false,"trimmed":false,"spriteSourceSize":{"x":0,"y":0,"w":59,"h":113},"sourceSize":{"w":59,"h":113}},"jump_3":{"frame":{"x":128,"y":3,"w":59,"h":113},"rotated":false,"trimmed":false,"spriteSourceSize":{"x":0,"y":0,"w":59,"h":113},"sourceSize":{"w":59,"h":113}},"fall_1":{"frame":{"x":189,"y":3,"w":63,"h":116},"rotated":false,"trimmed":false,"spriteSourceSize":{"x":0,"y":0,"w":63,"h":116},"sourceSize":{"w":63,"h":116}},"run_3":{"frame":{"x":2,"y":124,"w":63,"h":117},"rotated":false,"trimmed":false,"spriteSourceSize":{"x":0,"y":0,"w":63,"h":117},"sourceSize":{"w":63,"h":117}},"run_4":{"frame":{"x":67,"y":124,"w":64,"h":117},"rotated":false,"trimmed":false,"spriteSourceSize":{"x":0,"y":0,"w":64,"h":117},"sourceSize":{"w":64,"h":117}},"run_5":{"frame":{"x":133,"y":124,"w":64,"h":123},"rotated":false,"trimmed":false,"spriteSourceSize":{"x":0,"y":0,"w":64,"h":123},"sourceSize":{"w":64,"h":123}},"sprite11":{"frame":{"x":260,"y":124,"w":2,"h":1},"rotated":false,"trimmed":false,"spriteSourceSize":{"x":0,"y":0,"w":2,"h":1},"sourceSize":{"w":2,"h":1}},"run_6":{"frame":{"x":199,"y":133,"w":63,"h":124},"rotated":false,"trimmed":false,"spriteSourceSize":{"x":0,"y":0,"w":63,"h":124},"sourceSize":{"w":63,"h":124}}},"meta":{"app":"https://www.leshylabs.com/apps/sstool/","version":"Leshy SpriteSheet Tool v0.8.4","image":"spritesheet.png","size":{"w":512,"h":512},"scale":1}}